{
  "detailed_reports_summary": {
    "timestamp": "2025-10-01T16:09:20.650Z",
    "generator_version": "1.0.0",
    "reports_processed": 11,
    "metrics": {
      "total_reports": 11,
      "optimization_reports": 6,
      "correction_reports": 2,
      "retry_reports": 0,
      "total_corrections_applied": 7,
      "total_corrections_failed": 0,
      "total_attempts": 0,
      "success_rate": "100.00%",
      "average_attempts": 0,
      "by_type": {},
      "by_priority": {},
      "timeline": [
        {
          "timestamp": "2025-10-01T14:57:53.295Z",
          "type": "correction",
          "success": true
        },
        {
          "timestamp": "2025-10-01T14:57:53.358Z",
          "type": "correction",
          "success": true
        },
        {
          "timestamp": "2025-10-01T15:36:10.693Z",
          "type": "unknown",
          "success": true
        },
        {
          "timestamp": "2025-10-01T14:50:30.234Z",
          "type": "optimization",
          "success": true
        },
        {
          "timestamp": "2025-10-01T14:50:30.235Z",
          "type": "optimization",
          "success": true
        },
        {
          "timestamp": "2025-10-01T14:51:59.021Z",
          "type": "optimization",
          "success": true
        },
        {
          "timestamp": "2025-10-01T14:51:59.129Z",
          "type": "optimization",
          "success": true
        },
        {
          "timestamp": "2025-10-01T14:53:41.348Z",
          "type": "optimization",
          "success": true
        },
        {
          "timestamp": "2025-10-01T14:53:49.653Z",
          "type": "optimization",
          "success": true
        },
        {
          "timestamp": "2025-10-01T15:36:56.835Z",
          "type": "unknown",
          "success": true
        },
        {
          "timestamp": "2025-10-01T15:56:34.072Z",
          "type": "unknown",
          "success": true
        }
      ]
    },
    "individual_reports": [
      {
        "file": "auto-correction-1759330673295.json",
        "timestamp": "2025-10-01T14:57:53.295Z",
        "type": "correction",
        "success": true
      },
      {
        "file": "auto-correction-1759330673358.json",
        "timestamp": "2025-10-01T14:57:53.358Z",
        "type": "correction",
        "success": true
      },
      {
        "file": "auto-correction-v2-1759332970693.json",
        "timestamp": "2025-10-01T15:36:10.693Z",
        "type": "unknown",
        "success": true
      },
      {
        "file": "optimization-autofix-integration-1759330230234.json",
        "timestamp": "2025-10-01T14:50:30.234Z",
        "type": "optimization",
        "success": true
      },
      {
        "file": "optimization-autofix-integration-1759330230235.json",
        "timestamp": "2025-10-01T14:50:30.235Z",
        "type": "optimization",
        "success": true
      },
      {
        "file": "optimization-autofix-integration-1759330319021.json",
        "timestamp": "2025-10-01T14:51:59.021Z",
        "type": "optimization",
        "success": true
      },
      {
        "file": "optimization-autofix-integration-1759330319129.json",
        "timestamp": "2025-10-01T14:51:59.129Z",
        "type": "optimization",
        "success": true
      },
      {
        "file": "optimization-autofix-integration-1759330421348.json",
        "timestamp": "2025-10-01T14:53:41.348Z",
        "type": "optimization",
        "success": true
      },
      {
        "file": "optimization-autofix-integration-1759330429653.json",
        "timestamp": "2025-10-01T14:53:49.653Z",
        "type": "optimization",
        "success": true
      },
      {
        "file": "retry-rollback-v3-1759333016835.json",
        "timestamp": "2025-10-01T15:36:56.835Z",
        "type": "unknown",
        "success": true
      },
      {
        "file": "retry-rollback-v3-1759334194072.json",
        "timestamp": "2025-10-01T15:56:34.072Z",
        "type": "unknown",
        "success": true
      }
    ]
  }
}